pyrestfile/__init__.py
pyrestfile/parser.py
pyrestfile/request_block_grammar.py
pyrestfile/top_level_grammar.py
pyrestfile/vars.py
pyrestfile-0.2.1.dist-info/licenses/LICENSE
pyrestfile-0.2.1.dist-info/METADATA
pyrestfile-0.2.1.dist-info/WHEEL
pyrestfile-0.2.1.dist-info/top_level.txt
pyrestfile-0.2.1.dist-info/RECORD
