Metadata-Version: 2.4
Name: pyrestfile
Version: 0.2.1
Summary: Parse VS Code-style .rest files into request objects
Author-email: Abel Castillo <abelcastillomath@gmail.com>
License-Expression: MIT
Project-URL: Source, https://github.com/abelcastilloavant/pyrestfile
Classifier: Development Status :: 4 - Beta
Classifier: Intended Audience :: Developers
Classifier: Operating System :: OS Independent
Classifier: Programming Language :: Python :: 3
Classifier: Programming Language :: Python :: 3 :: Only
Classifier: Programming Language :: Python :: 3.12
Classifier: Topic :: Internet :: WWW/HTTP
Classifier: Typing :: Typed
Classifier: Natural Language :: English
License-File: LICENSE
Provides-Extra: dev
Requires-Dist: pytest>=8.0; extra == "dev"
Requires-Dist: pre-commit; extra == "dev"
Dynamic: license-file
